conflux/__init__.py
conflux/account.py
conflux/address.py
conflux/base32.py
conflux/cfx.py
conflux/consts.py
conflux/main.py
conflux/types.py
conflux/_utils/__init__.py
conflux/_utils/address.py
conflux/_utils/method_formatters.py
conflux/_utils/rpc_abi.py
conflux/_utils/signing.py
conflux/_utils/transactions.py
tests/__init__.py
tests/account_test.py
tests/address_test.py
tests/base32_test.py
tests/rpc_test.py
python_conflux_sdk-0.0.1.dist-info/METADATA
python_conflux_sdk-0.0.1.dist-info/WHEEL
python_conflux_sdk-0.0.1.dist-info/top_level.txt
python_conflux_sdk-0.0.1.dist-info/RECORD
