Metadata-Version: 2.1
Name: python-conflux-sdk
Version: 0.0.1
Summary: The python conflux SDK
Home-page: UNKNOWN
Author: Conflux-Dev
Author-email: wangpan@conflux-chain.org
License: UNKNOWN
Keywords: python,conflux,blockchain
Platform: UNKNOWN
Classifier: Programming Language :: Python :: 3
Classifier: Operating System :: MacOS :: MacOS X
Classifier: Operating System :: Microsoft :: Windows
Requires-Dist: eth-account (<0.6.0,>=0.5.3)
Requires-Dist: web3 (>=5.14)
